CHANGES.txt
LICENSE.GPL
LICENSE.txt
README.txt
TODO.txt
bootstrap.py
buildout.cfg
setup.py
src/slc/__init__.py
src/slc.rdbploneformgenadapter.egg-info/PKG-INFO
src/slc.rdbploneformgenadapter.egg-info/SOURCES.txt
src/slc.rdbploneformgenadapter.egg-info/dependency_links.txt
src/slc.rdbploneformgenadapter.egg-info/entry_points.txt
src/slc.rdbploneformgenadapter.egg-info/namespace_packages.txt
src/slc.rdbploneformgenadapter.egg-info/not-zip-safe
src/slc.rdbploneformgenadapter.egg-info/requires.txt
src/slc.rdbploneformgenadapter.egg-info/top_level.txt
src/slc/rdbploneformgenadapter/__init__.py
src/slc/rdbploneformgenadapter/adapters.py
src/slc/rdbploneformgenadapter/configure.zcml
src/slc/rdbploneformgenadapter/interfaces.py
src/slc/rdbploneformgenadapter/setuphandlers.py
src/slc/rdbploneformgenadapter/browser/__init__.py
src/slc/rdbploneformgenadapter/browser/configure.zcml
src/slc/rdbploneformgenadapter/browser/views.py
src/slc/rdbploneformgenadapter/content/__init__.py
src/slc/rdbploneformgenadapter/content/configure.zcml
src/slc/rdbploneformgenadapter/content/content.py
src/slc/rdbploneformgenadapter/profiles/default/import_steps.xml
src/slc/rdbploneformgenadapter/profiles/default/metadata.xml
src/slc/rdbploneformgenadapter/profiles/default/slc.RDBPloneFormGenAdapter_marker.txt
src/slc/rdbploneformgenadapter/profiles/default/types.xml
src/slc/rdbploneformgenadapter/profiles/default/types/FormFolder.xml
src/slc/rdbploneformgenadapter/profiles/default/types/RDBPloneFormGenAdapter.xml
src/slc/rdbploneformgenadapter/tests/__init__.py
src/slc/rdbploneformgenadapter/tests/base.py
src/slc/rdbploneformgenadapter/tests/content.py
src/slc/rdbploneformgenadapter/tests/test_action.py
src/slc/rdbploneformgenadapter/tests/test_browser.py
src/slc/rdbploneformgenadapter/tests/test_content.py