Metadata-Version: 1.0
Name: slc.rdbploneformgenadapter
Version: 0.0.2
Summary: Provides an Action Adapter for PloneFormGen to store data in an RDB
Home-page: http://pypi.python.org/pypi/slc.rdbploneformgenadapter
Author: Syslab.com GmbH
Author-email: info@syslab.com
License: GPL
Platform: UNKNOWN
Classifier: Framework :: Plone
Classifier: Intended Audience :: Developers
Classifier: Intended Audience :: End Users/Desktop
Classifier: License :: OSI Approved :: GNU General Public License (GPL)
